histo_tools/__init__.py
histo_tools/deconvolution.py
histo_tools/importing.py
histo_tools-0.0.11.dist-info/LICENSE
histo_tools-0.0.11.dist-info/METADATA
histo_tools-0.0.11.dist-info/WHEEL
histo_tools-0.0.11.dist-info/top_level.txt
histo_tools-0.0.11.dist-info/RECORD
